cfnlp/__init__.py
cfnlp/main.py
cfnlp/rolegen.py
cfnlp/mappings/__init__.py
cfnlp/mappings/awslambda.py
cfnlp/mappings/cloudwatch.py
cfnlp/mappings/ec2.py
cfnlp/mappings/iam.py
cfnlp/mappings/s3.py
cfnlp/mappings/sns.py
cfnlp/mappings/sqs.py
cfnlp-0.1.2.dist-info/LICENSE
cfnlp-0.1.2.dist-info/METADATA
cfnlp-0.1.2.dist-info/WHEEL
cfnlp-0.1.2.dist-info/entry_points.txt
cfnlp-0.1.2.dist-info/top_level.txt
cfnlp-0.1.2.dist-info/zip-safe
cfnlp-0.1.2.dist-info/RECORD
