Metadata-Version: 2.1
Name: cfnlp
Version: 0.1.2
Summary: Generates an IAM policy for the CloudFormation service role that adheres to least privilege
Home-page: https://github.com/iann0036/cfn-leastprivilege
Author: Ian Mckay
Author-email: cfnlp@ian.mn
License: MIT
Platform: UNKNOWN
Requires-Dist: boto3 (>=1.10.41cfn_flip>=1.2.2)
